{"TRACEROUTE": {}, "UserInfo": {"lat": 0, "timestamp": "2017-04-11 03:28:50.947942", "user id": "0x58b035fbf409", "lon": 0, "ip": "null"}, "SpeedTests": {"UDP": {"download": {"420p": {"jitter_lat": 0.0016589195715838478, "jitter_iat": 0.0059657156602119935, "PLR": 0.00029999999999996696}, "720p": {"jitter_lat": 0.009606746365236493, "jitter_iat": 0.004663922533052354, "PLR": 0.0}, "1080p": {"jitter_lat": 0.008601558622430583, "jitter_iat": 0.0033943320169195494, "PLR": 0.0}, "4k": {"jitter_lat": 0.11076958858338944, "jitter_iat": 0.004347523219157584, "PLR": 0.4394}}, "2way": {"gaming": {"latency": -1, "jitter_lat": -1, "jitter_iat": -1, "PLR": -1}, "high_VOIP": {"latency": 0.08191689205169678, "jitter_lat": 0.011252676751168865, "jitter_iat": 0.013571094217977133, "PLR": 0.0}, "low_VOIP": {"latency": 0.081709893703460698, "jitter_lat": 0.013035562671072152, "jitter_iat": 0.013444798741188792, "PLR": 0.0}}, "upload": {"standard_video_calling": {"jitter_lat": "0.00414177435538", "jitter_iat": "0.017636462622", "PLR": 0.0}, "screensharing": {"jitter_lat": -1, "jitter_iat": -1, "PLR": -1}, "hd_video_calling": {"jitter_lat": "0.00723452080882", "jitter_iat": "0.0166811815349", "PLR": 0.0}}}, "TCP": {"download": 17987121.892157, "upload": 30955039.99009}}}